mcp_tmap/__init__.py
mcp_tmap/__main__.py
mcp_tmap/server.py
mcp_tmap/tmap_client.py
mseep_mcp_tmap-0.1.1.dist-info/licenses/LICENSE
mseep_mcp_tmap-0.1.1.dist-info/METADATA
mseep_mcp_tmap-0.1.1.dist-info/WHEEL
mseep_mcp_tmap-0.1.1.dist-info/entry_points.txt
mseep_mcp_tmap-0.1.1.dist-info/top_level.txt
mseep_mcp_tmap-0.1.1.dist-info/RECORD
